{
  "type": "minecraft:chest",
  "pools": [
    {
      "bonus_rolls": 0.0,
      "entries": [
        {
          "type": "minecraft:item",
          "functions": [
            {
              "add": false,
              "count": {
                "type": "minecraft:uniform",
                "max": 9.0,
                "min": 4.0
              },
              "function": "minecraft:set_count"
            }
          ],
          "name": "bloodmagic:ironsand",
          "quality": 1,
          "weight": 20
        },
        {
          "type": "minecraft:item",
          "functions": [
            {
              "add": false,
              "count": {
                "type": "minecraft:uniform",
                "max": 9.0,
                "min": 4.0
              },
              "function": "minecraft:set_count"
            }
          ],
          "name": "bloodmagic:goldsand",
          "quality": 2,
          "weight": 15
        },
        {
          "type": "minecraft:item",
          "functions": [
            {
              "add": false,
              "count": {
                "type": "minecraft:uniform",
                "max": 15.0,
                "min": 7.0
              },
              "function": "minecraft:set_count"
            }
          ],
          "name": "bloodmagic:coalsand",
          "quality": -2,
          "weight": 8
        },
        {
          "type": "minecraft:item",
          "functions": [
            {
              "add": false,
              "count": {
                "type": "minecraft:uniform",
                "max": 9.0,
                "min": 4.0
              },
              "function": "minecraft:set_count"
            }
          ],
          "name": "minecraft:redstone",
          "quality": 2,
          "weight": 10
        },
        {
          "type": "minecraft:item",
          "functions": [
            {
              "add": false,
              "count": {
                "type": "minecraft:uniform",
                "max": 9.0,
                "min": 4.0
              },
              "function": "minecraft:set_count"
            }
          ],
          "name": "minecraft:glowstone_dust",
          "quality": 2,
          "weight": 10
        },
        {
          "type": "minecraft:item",
          "functions": [
            {
              "add": false,
              "count": {
                "type": "minecraft:uniform",
                "max": 9.0,
                "min": 4.0
              },
              "function": "minecraft:set_count"
            }
          ],
          "name": "minecraft:gunpowder",
          "quality": 2,
          "weight": 8
        },
        {
          "type": "minecraft:item",
          "functions": [
            {
              "add": false,
              "count": {
                "type": "minecraft:uniform",
                "max": 14.0,
                "min": 6.0
              },
              "function": "minecraft:set_count"
            }
          ],
          "name": "minecraft:nether_wart",
          "quality": 2,
          "weight": 10
        },
        {
          "type": "minecraft:item",
          "functions": [
            {
              "add": false,
              "count": {
                "type": "minecraft:uniform",
                "max": 5.0,
                "min": 2.0
              },
              "function": "minecraft:set_count"
            }
          ],
          "name": "minecraft:golden_carrot",
          "quality": 2,
          "weight": 4
        },
        {
          "type": "minecraft:item",
          "functions": [
            {
              "add": false,
              "count": {
                "type": "minecraft:uniform",
                "max": 5.0,
                "min": 2.0
              },
              "function": "minecraft:set_count"
            }
          ],
          "name": "minecraft:phantom_membrane",
          "quality": 2,
          "weight": 4
        },
        {
          "type": "minecraft:item",
          "functions": [
            {
              "add": false,
              "count": {
                "type": "minecraft:uniform",
                "max": 5.0,
                "min": 2.0
              },
              "function": "minecraft:set_count"
            }
          ],
          "name": "minecraft:rabbit_foot",
          "quality": 2,
          "weight": 3
        },
        {
          "type": "minecraft:item",
          "functions": [
            {
              "add": false,
              "count": {
                "type": "minecraft:uniform",
                "max": 9.0,
                "min": 4.0
              },
              "function": "minecraft:set_count"
            }
          ],
          "name": "bloodmagic:plantoil",
          "quality": 2,
          "weight": 6
        },
        {
          "type": "minecraft:item",
          "functions": [
            {
              "add": false,
              "count": {
                "type": "minecraft:uniform",
                "max": 9.0,
                "min": 4.0
              },
              "function": "minecraft:set_count"
            }
          ],
          "name": "bloodmagic:weak_tau",
          "quality": 2,
          "weight": 8
        },
        {
          "type": "minecraft:item",
          "functions": [
            {
              "add": false,
              "count": {
                "type": "minecraft:uniform",
                "max": 5.0,
                "min": 2.0
              },
              "function": "minecraft:set_count"
            }
          ],
          "name": "minecraft:blaze_powder",
          "quality": -1,
          "weight": 5
        },
        {
          "type": "minecraft:item",
          "functions": [
            {
              "add": false,
              "count": {
                "type": "minecraft:uniform",
                "max": 5.0,
                "min": 2.0
              },
              "function": "minecraft:set_count"
            }
          ],
          "name": "minecraft:magma_cream",
          "quality": -1,
          "weight": 5
        },
        {
          "type": "minecraft:item",
          "functions": [
            {
              "add": false,
              "count": {
                "type": "minecraft:uniform",
                "max": 5.0,
                "min": 2.0
              },
              "function": "minecraft:set_count"
            }
          ],
          "name": "minecraft:slime_ball",
          "quality": -1,
          "weight": 5
        },
        {
          "type": "minecraft:item",
          "functions": [
            {
              "add": false,
              "count": {
                "type": "minecraft:uniform",
                "max": 5.0,
                "min": 2.0
              },
              "function": "minecraft:set_count"
            }
          ],
          "name": "minecraft:fermented_spider_eye",
          "quality": -1,
          "weight": 5
        },
        {
          "type": "minecraft:item",
          "functions": [
            {
              "add": false,
              "count": {
                "type": "minecraft:uniform",
                "max": 5.0,
                "min": 2.0
              },
              "function": "minecraft:set_count"
            }
          ],
          "name": "minecraft:spider_eye",
          "quality": -1,
          "weight": 5
        },
        {
          "type": "minecraft:item",
          "functions": [
            {
              "add": false,
              "count": {
                "type": "minecraft:uniform",
                "max": 5.0,
                "min": 2.0
              },
              "function": "minecraft:set_count"
            }
          ],
          "name": "minecraft:sugar",
          "quality": -1,
          "weight": 5
        },
        {
          "type": "minecraft:item",
          "functions": [
            {
              "add": false,
              "count": {
                "type": "minecraft:uniform",
                "max": 5.0,
                "min": 2.0
              },
              "function": "minecraft:set_count"
            }
          ],
          "name": "minecraft:honeycomb",
          "quality": -1,
          "weight": 5
        },
        {
          "type": "minecraft:item",
          "functions": [
            {
              "add": false,
              "count": {
                "type": "minecraft:uniform",
                "max": 5.0,
                "min": 2.0
              },
              "function": "minecraft:set_count"
            }
          ],
          "name": "minecraft:glistering_melon_slice",
          "quality": -1,
          "weight": 5
        },
        {
          "type": "minecraft:item",
          "name": "bloodmagic:basiccuttingfluid",
          "quality": 4,
          "weight": 6
        },
        {
          "type": "minecraft:item",
          "functions": [
            {
              "add": false,
              "count": {
                "type": "minecraft:uniform",
                "max": 3.0,
                "min": 1.0
              },
              "function": "minecraft:set_count"
            }
          ],
          "name": "bloodmagic:mundanepowercatalyst",
          "quality": 2,
          "weight": 10
        },
        {
          "type": "minecraft:item",
          "functions": [
            {
              "add": false,
              "count": {
                "type": "minecraft:uniform",
                "max": 3.0,
                "min": 1.0
              },
              "function": "minecraft:set_count"
            }
          ],
          "name": "bloodmagic:mundanelengtheningcatalyst",
          "quality": 2,
          "weight": 10
        },
        {
          "type": "minecraft:item",
          "functions": [
            {
              "add": false,
              "count": {
                "type": "minecraft:uniform",
                "max": 3.0,
                "min": 1.0
              },
              "function": "minecraft:set_count"
            }
          ],
          "name": "bloodmagic:combinationalcatalyst",
          "quality": 3,
          "weight": 7
        },
        {
          "type": "minecraft:item",
          "functions": [
            {
              "add": false,
              "count": {
                "type": "minecraft:uniform",
                "max": 7.0,
                "min": 3.0
              },
              "function": "minecraft:set_count"
            }
          ],
          "name": "bloodmagic:simplecatalyst",
          "quality": 2,
          "weight": 10
        },
        {
          "type": "minecraft:item",
          "functions": [
            {
              "function": "minecraft:set_potion",
              "id": "minecraft:poison"
            }
          ],
          "name": "minecraft:splash_potion",
          "weight": 5
        }
      ],
      "rolls": {
        "type": "minecraft:uniform",
        "max": 6.0,
        "min": 3.0
      }
    }
  ],
  "random_sequence": "bloodmagic:chests/standard_dungeon/decent_alchemy"
}