{
  "parent": "bloodmagic:bloodmagic/root",
  "criteria": {
    "hold_item":{
      "trigger": "minecraft:inventory_changed",
      "conditions": {
        "items": [
          {
            "items": ["bloodmagic:soulsnare"]
          }
        ]
      }
    }
  },
  "display": {
    "icon": {
      "item": "bloodmagic:soulsnare"
    },
    "title": {
      "translate": "advancements.bloodmagic.soulsnare.title"
    },
    "frame": "task",
    "description": {
      "translate": "advancements.bloodmagic.soulsnare.description"
    },
    "show_toast": false,
    "announce_to_chat": false
  },
  "requirements": [
    [
      "hold_item"
    ]
  ]
}