{
  "parent": "minecraft:recipes/root",
  "criteria": {
    "has_master_orb": {
      "conditions": {
        "items": [
          {
            "items": [
              "bloodmagic:masterbloodorb"
            ]
          }
        ]
      },
      "trigger": "minecraft:inventory_changed"
    },
    "has_the_recipe": {
      "conditions": {
        "recipe": "bloodmagic:blood_rune_acceleration"
      },
      "trigger": "minecraft:recipe_unlocked"
    }
  },
  "requirements": [
    [
      "has_master_orb",
      "has_the_recipe"
    ]
  ],
  "rewards": {
    "recipes": [
      "bloodmagic:blood_rune_acceleration"
    ]
  },
  "sends_telemetry_event": false
}